odoo/addons/ssi_property_management/README.rst
odoo/addons/ssi_property_management/__init__.py
odoo/addons/ssi_property_management/__manifest__.py
odoo/addons/ssi_property_management/menu.xml
odoo/addons/ssi_property_management/models/__init__.py
odoo/addons/ssi_property_management/models/property_object.py
odoo/addons/ssi_property_management/models/property_object_type.py
odoo/addons/ssi_property_management/models/res_company.py
odoo/addons/ssi_property_management/models/res_config_settings.py
odoo/addons/ssi_property_management/security/ir.model.access.csv
odoo/addons/ssi_property_management/security/ir_module_category_data.xml
odoo/addons/ssi_property_management/security/res_group_data.xml
odoo/addons/ssi_property_management/static/description/icon.png
odoo/addons/ssi_property_management/static/description/risk-assessment-template.odt
odoo/addons/ssi_property_management/views/property_object_type_views.xml
odoo/addons/ssi_property_management/views/property_object_views.xml
odoo14_addon_ssi_property_management-14.0.1.0.0.dist-info/METADATA
odoo14_addon_ssi_property_management-14.0.1.0.0.dist-info/WHEEL
odoo14_addon_ssi_property_management-14.0.1.0.0.dist-info/top_level.txt
odoo14_addon_ssi_property_management-14.0.1.0.0.dist-info/RECORD
